[[{"axis":"UK","value":32027.6068674223},{"axis":"Rest of Europe","value":1082.7596743744},{"axis":"North America","value":400.5856587931},{"axis":"South America","value":43.1158602059},{"axis":"Asia","value":153.2849071946},{"axis":"Australia","value":986.8168985873},{"axis":"Africa","value":12.2465454931}],[{"axis":"UK","value":57420.4688586603},{"axis":"Rest of Europe","value":2062.5953815459},{"axis":"North America","value":700.0251866728},{"axis":"South America","value":70.3604446517},{"axis":"Asia","value":197.0899841549},{"axis":"Australia","value":1906.9186348429},{"axis":"Africa","value":22.9660496032}],[{"axis":"UK","value":13940.9214299288},{"axis":"Rest of Europe","value":473.4076777587},{"axis":"North America","value":227.0970627408},{"axis":"South America","value":26.48141587},{"axis":"Asia","value":111.7185015243},{"axis":"Australia","value":376.9710566292},{"axis":"Africa","value":6.0070269112}],[{"axis":"UK","value":83513.9104454024},{"axis":"Rest of Europe","value":1052.4045997199},{"axis":"North America","value":463.6591476697},{"axis":"South America","value":50.5406335521},{"axis":"Asia","value":232.6765520741},{"axis":"Australia","value":789.6675731729},{"axis":"Africa","value":12.5364504052}],[{"axis":"UK","value":36874.8907293869},{"axis":"Rest of Europe","value":754.5796947504},{"axis":"North America","value":259.7496961437},{"axis":"South America","value":25.3384129549},{"axis":"Asia","value":74.7122925902},{"axis":"Australia","value":654.0564869485},{"axis":"Africa","value":7.9796249958}],[{"axis":"UK","value":41550.5097695913},{"axis":"Rest of Europe","value":814.6462818957},{"axis":"North America","value":349.994538131},{"axis":"South America","value":36.2792553592},{"axis":"Asia","value":145.5905744164},{"axis":"Australia","value":670.9123815048},{"axis":"Africa","value":9.6474574198}]]